hrv/__init__.py
hrv/classical.py
hrv/detrend.py
hrv/exceptions.py
hrv/filters.py
hrv/io.py
hrv/nonstationary.py
hrv/rri.py
hrv/utils.py
hrv/sampledata/__init__.py
hrv/sampledata/_load.py
hrv-0.2.10.dist-info/LICENSE.md
hrv-0.2.10.dist-info/METADATA
hrv-0.2.10.dist-info/WHEEL
hrv-0.2.10.dist-info/top_level.txt
hrv-0.2.10.dist-info/RECORD
