Metadata-Version: 2.1
Name: hrv
Version: 0.2.10
Summary: A python package for heart rate variability analysis
Home-page: https://github.com/rhenanbartels/hrv
Author: Rhenan Bartels
Author-email: rhenan.bartels@gmail.com
License: BSD
Download-URL: https://github.com/rhenanbartels/hrv/tarball/0.2.10
Platform: UNKNOWN
Classifier: Development Status :: 3 - Alpha
Classifier: Intended Audience :: Developers
Classifier: Programming Language :: Python :: 3
Requires-Dist: matplotlib (>=2.2.2)
Requires-Dist: numpy (>=1.14.4)
Requires-Dist: scipy (>=1.1.0)
Requires-Dist: spectrum (>=0.7.3)
